passwordcrypto/__init__.py
passwordcrypto/passwordcrypto.py
tests/__init__.py
tests/test_passwordcrypto.py
passwordcrypto-1.0.6.dist-info/LICENSE
passwordcrypto-1.0.6.dist-info/METADATA
passwordcrypto-1.0.6.dist-info/WHEEL
passwordcrypto-1.0.6.dist-info/top_level.txt
passwordcrypto-1.0.6.dist-info/RECORD
