Metadata-Version: 2.1
Name: passwordcrypto
Version: 1.0.6
Summary: A package to help make an encrypted password manager
Home-page: https://github.com/Muxutruk2/passwordcrypto2
Author: Muxutruk
License: UNKNOWN
Keywords: password,cryptography,security
Platform: UNKNOWN
Classifier: License :: OSI Approved :: MIT License
Classifier: Programming Language :: Python :: 3
Classifier: Intended Audience :: Developers
License-File: LICENSE
Requires-Dist: cryptography
